ftpparser/__init__.py
ftpparser/parse.py
ftpparser/parse_time.py
ftpparser-0.0.3.dist-info/LICENSE
ftpparser-0.0.3.dist-info/METADATA
ftpparser-0.0.3.dist-info/WHEEL
ftpparser-0.0.3.dist-info/top_level.txt
ftpparser-0.0.3.dist-info/RECORD
