Metadata-Version: 2.1
Name: ftpparser
Version: 0.0.3
Summary: FTP LIST parsing library
Home-page: https://github.com/stevemayne/pyftpparser
Author: Steve Mayne
Author-email: steve.mayne@gmail.com
License: UNKNOWN
Platform: UNKNOWN
Classifier: Programming Language :: Python :: 3
Classifier: License :: OSI Approved :: MIT License
Classifier: Operating System :: OS Independent
